pipAutoInstall/__init__.py
pipAutoInstall-1.0.0.dist-info/LICENSE
pipAutoInstall-1.0.0.dist-info/METADATA
pipAutoInstall-1.0.0.dist-info/WHEEL
pipAutoInstall-1.0.0.dist-info/top_level.txt
pipAutoInstall-1.0.0.dist-info/RECORD
