Metadata-Version: 2.1
Name: pipAutoInstall
Version: 1.0.0
Summary: Advanced module import.
Author-email: EasyOmny <omenplay325@gmail.com>
License: Copyright (c) 2023 EasyOmny
Project-URL: Homepage, https://github.com/EasyOmny/pipAutoInstall
Keywords: python,import
Classifier: License :: OSI Approved :: MIT License
Classifier: Programming Language :: Python
Classifier: Programming Language :: Python :: 3
Requires-Python: >=3.9
License-File: LICENSE
